Workbook

Sheet Dashboard

Sheet Pivots
B8: Overall compliance (for maturity_score textbox)
B11: Average of Current Maturity Score
B12: 2.8113208
B18: Average of scores across each Function
B20: Row Labels | C20: Average of Current Maturity Score
B21: DETECT (DE) | C21: 3
B22: GOVERN (GV) | C22: 2.9677419
B23: IDENTIFY (ID) | C23: 2.2380952
B24: PROTECT (PR) | C24: 3
B25: RECOVER (RC) | C25: 2.625
B26: RESPOND (RS) | C26: 3
B27: Grand Total | C27: 2.8113208
B30: Average of current scores across each Category
B32: Row Labels | C32: Average of Current Maturity Score
B33: Adverse Event Analysis (DE.AE) | C33: 3
B34: Asset Management (ID.AM) | C34: 2.4285714
B35: Awareness and Training (PR.AT) | C35: 3
B36: Continuous Monitoring (DE.CM) | C36: 3
B37: Cybersecurity Supply Chain Risk Management (GV.SC) | C37: 3
B38: Data Security (PR.DS) | C38: 3
B39: Identity Management, Authentication, and Access Control (PR.AA) | C39: 3
B40: Improvement (ID.IM) | C40: 2.5
B41: Incident Analysis (RS.AN) | C41: 3
B42: Incident Management (RS.MA) | C42: 3
B43: Incident Mitigation (RS.MI) | C43: 3
B44: Incident Recovery Communication (RC.CO) | C44: 2
... B55: Grand Total | C55: 2.8113208
B59: Current vs Target
B61: Row Labels | C61: Current Maturity | D61: Target Maturity
B62: DETECT (DE) | C62: 3 | D62: 4
B63: GOVERN (GV) | C63: 2.9677419 | D63: 4
B64: IDENTIFY (ID) | C64: 2.2380952 | D64: 4
B65: PROTECT (PR) | C65: 3 | D65: 4
B66: RECOVER (RC) | C66: 2.625 | D66: 3.875
B67: RESPOND (RS) | C67: 3 | D67: 4
B68: Grand Total | C68: 2.8113208 | D68: 3.990566

Sheet Requirements
A2: Function | B2: Category | C2: Subcategory | D2: Subcategory description | E2: Implementation Examples | F2: Informative References | G2: Current Maturity Level | H2: Current Maturity Score | I2: Current Maturity Comments | J2: Target Maturity Level | K2: Target Maturity Score | L2: Target Maturity Comments
A3: GOVERN (GV) | B3: Organizational Context (GV.OC) | C3: GV.OC-01 | D3: The organizational mission is understood and informs cybersecurity risk management | E3: Ex1: Share the organization's mission (e.g., through vision and mission statements, marketing, and service strategies) to provide a basis for identifying risks that may impede that mission | F3: CCMv4.0: BCR-01 CCMv4.0: BCR-07 CRI Profile v2.0: GV.OC-01 CRI Profile v2.0: GV.OC-01.01 CSF v1.1: ID.BE-2 CSF v1.1: ID.BE-3 SP 800-221A: GV.CT-5 SP 800-221A: GV.CT-3 SP 800-53 Rev 5.1.1: PM-11 | G3: Level 3: Managed | H3: =IF(G3="","",VLOOKUP(G3,'Maturity Definitions'!$B$4:$D$8,3,FALSE)) -> 3 | J3: Level 4: Quantitatively Managed | K3: =IF(J3="","",VLOOKUP(J3,'Maturity Definitions'!$B$4:$D$8,3,FALSE)) -> 4
A4: GOVERN (GV) | B4: Organizational Context (GV.OC) | C4: GV.OC-02 | D4: Internal and external stakeholders are understood, and their needs and expectations regarding cybersecurity risk management are understood and considered | E4: Ex1: Identify relevant internal stakeholders and their cybersecurity-related expectations (e.g., performance and risk expectations of officers, directors, and advisors; cultural expectations of employees) Ex2: Identify relevant external stakeholders and their cybersecurity-related expectations (e.g., privacy expectations of customers, business expectations of partnerships, compliance expectations of regulators, ethics expectations of society) | F4: CCMv4.0: STA-08 CCMv4.0: STA-13 CRI Profile v2.0: GV.OC-02 CRI Profile v2.0: GV.OC-02.01 CRI Profile v2.0: GV.OC-02.02 CRI Profile v2.0: GV.OC-02.03 CSF v1.1: ID.SC-2 CSF v1.1: ID.GV-2 SP 800-218: PO.2.1 SP 800-221A: GV.OV-2 SP 800-221A: GV.CT-2 SP 800-221A: GV.CT-3 SP 800-53 Rev 5.1.1: PM-09 SP 800-53 Rev 5.1.1: PM-18 SP 800-53 Rev 5.1.1: PM-30 SP 800-53 Rev 5.1.1: SR-03 SP 800-53 Rev 5.1.1: SR-05 SP 800-53 Rev 5.1.1: SR-06 SP 800-53 Rev 5.1.1: SR-08 | G4: Level 2: Documented | H4: =IF(G4="","",VLOOKUP(G4,'Maturity Definitions'!$B$4:$D$8,3,FALSE)) -> 2 | J4: Level 4: Quantitatively Managed | K4: =IF(J4="","",VLOOKUP(J4,'Maturity Definitions'!$B$4:$D$8,3,FALSE)) -> 4
A5: GOVERN (GV) | B5: Organizational Context (GV.OC) | C5: GV.OC-03 | D5: Legal, regulatory, and contractual requirements regarding cybersecurity - including privacy and civil liberties obligations - are understood and managed | E5: Ex1: Determine a process to track and manage legal and regulatory requirements regarding protection of individuals' information (e.g., Health Insurance Portability and Accountability Act, California Consumer Privacy Act, General Data Protection Regulation) Ex2: Determine a process to track and manage contractual requirements for cybersecurity management of supplier, customer, and partner information Ex3: Align the organization's cybersecurity strategy with legal, regulatory, and contractual requirements | F5: CCMv4.0: CEK-12 CCMv4.0: CEK-13 CCMv4.0: CEK-14 CCMv4.0: CEK-15 CCMv4.0: CEK-16 CCMv4.0: CEK-17 CCMv4.0: CEK-18 CCMv4.0: CEK-19 CCMv4.0: CEK-20 CCMv4.0: CEK-21 CCMv4.0: DSP-01 CCMv4.0: DSP-10 CCMv4.0: DSP-11 CCMv4.0: DSP-12 CCMv4.0: DSP-16 CCMv4.0: DSP-18 CCMv4.0: GRC-07 CCMv4.0: HRS-13 CCMv4.0: STA-05 CCMv4.0: STA-13 CRI Profile v2.0: GV.OC-03 CRI Profile v2.0: GV.OC-03.01 CRI Profile v2.0: GV.OC-03.02 CSF v1.1: ID.GV-3 SP 800-218: PO.1.1 SP 800-218: PO.1.2 SP 800-53 Rev 5.1.1: AC-01 SP 800-53 Rev 5.1.1: AT-01 SP 800-53 Rev 5.1.1: AU-01 SP 800-53 Rev 5.1.1: CA-01 SP 800-53 Rev 5.1.1: CM-01 SP 800-53 Rev 5.1.1: CP-01 SP 800-53 Rev 5.1.1: IA-01 SP 800-53 Rev 5.1.1: IR-01 SP 800-53 Rev 5.1.1: MA-01 SP 800-53 Rev 5.1.1: MP-01 SP 800-53 Rev 5.1.1: PE-01 SP 800-53 Rev 5.1.1: PL-01 SP 800-53 Rev 5.1.1: PM-01 SP 800-53 Rev 5.1.1: PS-01 SP 800-53 Rev 5.1.1: PT-01 SP 800-53 Rev 5.1.1: RA-01 SP 800-53 Rev 5.1.1: SA-01 SP 800-53 Rev 5.1.1: SC-01 SP 800-53 Rev 5.1.1: SI-01 SP 800-53 Rev 5.1.1: SR-01 SP 800-53 Rev 5.1.1: PM-28 SP 800-53 Rev 5.1.1: PT | G5: Level 3: Managed | H5: =IF(G5="","",VLOOKUP(G5,'Maturity Definitions'!$B$4:$D$8,3,FALSE)) -> 3 | J5: Level 4: Quantitatively Managed | K5: =IF(J5="","",VLOOKUP(J5,'Maturity Definitions'!$B$4:$D$8,3,FALSE)) -> 4
A6: GOVERN (GV) | B6: Organizational Context (GV.OC) | C6: GV.OC-04 | D6: Critical objectives, capabilities, and services that external stakeholders depend on or expect from the organization are understood and communicated | E6: Ex1: Establish criteria for determining the criticality of capabilities and services as viewed by internal and external stakeholders Ex2: Determine (e.g., from a business impact analysis) assets and business operations that are vital to achieving mission objectives and the potential impact of a loss (or partial loss) of such operations Ex3: Establish and communicate resilience objectives (e.g., recovery time objectives) for delivering critical capabilities and services in various operating states (e.g., under attack, during recovery, normal operation) | F6: CCMv4.0: BCR-01 CCMv4.0: BCR-02 CCMv4.0: BCR-03 CCMv4.0: BCR-11 CCMv4.0: IVS-02 CCMv4.0: STA-05 CRI Profile v2.0: GV.OC-04 CRI Profile v2.0: GV.OC-04.01 CRI Profile v2.0: GV.OC-04.02 CRI Profile v2.0: GV.OC-04.03 CRI Profile v2.0: GV.OC-04.04 CSF v1.1: ID.BE-4 CSF v1.1: ID.BE-5 SP 800-221A: MA.RI-1 SP 800-53 Rev 5.1.1: PM-08 SP 800-53 Rev 5.1.1: PM-11 SP 800-53 Rev 5.1.1: CP-02(08) SP 800-53 Rev 5.1.1: PM-30(01) SP 800-53 Rev 5.1.1: RA-09 | G6: Level 3: Managed | H6: =IF(G6="","",VLOOKUP(G6,'Maturity Definitions'!$B$4:$D$8,3,FALSE)) -> 3 | J6: Level 4: Quantitatively Managed | K6: =IF(J6="","",VLOOKUP(J6,'Maturity Definitions'!$B$4:$D$8,3,FALSE)) -> 4
A7: GOVERN (GV) | B7: Organizational Context (GV.OC) | C7: GV.OC-05 | D7: Outcomes, capabilities, and services that the organization depends on are understood and communicated | E7: Ex1: Create an inventory of the organization's dependencies on external resources (e.g., facilities, cloud-based hosting providers) and their relationships to organizational assets and business functions Ex2: Identify and document external dependencies that are potential points of failure for the organization's critical capabilities and services, and share that information with appropriate personnel | F7: CCMv4.0: BCR-11 CCMv4.0: STA-01 CCMv4.0: STA-04 CRI Profile v2.0: GV.OC-05 CRI Profile v2.0: GV.OC-05.01 CRI Profile v2.0: GV.OC-05.02 CRI Profile v2.0: GV.OC-05.03 CRI Profile v2.0: GV.OC-05.04 CSF v1.1: ID.BE-1 CSF v1.1: ID.BE-4 SP 800-221A: GV.CT-5 SP 800-221A: MA.RI-1 SP 800-53 Rev 5.1.1: PM-11 SP 800-53 Rev 5.1.1: PM-30 SP 800-53 Rev 5.1.1: RA-07 SP 800-53 Rev 5.1.1: SA-09 SP 800-53 Rev 5.1.1: SR-05 | G7: Level 3: Managed | H7: =IF(G7="","",VLOOKUP(G7,'Maturity Definitions'!$B$4:$D$8,3,FALSE)) -> 3 | J7: Level 4: Quantitatively Managed | K7: =IF(J7="","",VLOOKUP(J7,'Maturity Definitions'!$B$4:$D$8,3,FALSE)) -> 4
A8: GOVERN (GV) | B8: Risk Management Strategy (GV.RM) | C8: GV.RM-01 | D8: Risk management objectives are established and agreed to by organizational stakeholders | E8: Ex1: Update near-term and long-term cybersecurity risk management objectives as part of annual strategic planning and when major changes occur Ex2: Establish measurable objectives for cybersecurity risk management (e.g., manage the quality of user training, ensure adequate risk protection for industrial control systems) Ex3: Senior leaders agree about cybersecurity objectives and use them for measuring and managing risk and performance | F8: CCMv4.0: GRC-02 CCMv4.0: CEK-07 CRI Profile v2.0: GV.RM-01 CRI Profile v2.0: GV.RM-01.01 CRI Profile v2.0: GV.RM-01.02 CRI Profile v2.0: GV.RM-01.03 CRI Profile v2.0: GV.RM-01.04 CRI Profile v2.0: GV.RM-01.05 CSF v1.1: ID.RM-1 SP 800-221A: GV.RR-2 SP 800-53 Rev 5.1.1: PM-09 SP 800-53 Rev 5.1.1: RA-07 SP 800-53 Rev 5.1.1: SR-02 | G8: Level 3: Managed | H8: =IF(G8="","",VLOOKUP(G8,'Maturity Definitions'!$B$4:$D$8,3,FALSE)) -> 3 | J8: Level 4: Quantitatively Managed | K8: =IF(J8="","",VLOOKUP(J8,'Maturity Definitions'!$B$4:$D$8,3,FALSE)) -> 4
A9: GOVERN (GV) | B9: Risk Management Strategy (GV.RM) | C9: GV.RM-02 | D9: Risk appetite and risk tolerance statements are established, communicated, and maintained | E9: Ex1: Determine and communicate risk appetite statements that convey expectations about the appropriate level of risk for the organization Ex2: Translate risk appetite statements into specific, measurable, and broadly understandable risk tolerance statements Ex3: Refine organizational objectives and risk appetite periodically based on known risk exposure and residual risk | F9: CCMv4.0: GRC-02 CCMv4.0: BCR-03 CCMv4.0: IVS-08 CRI Profile v2.0: GV.RM-02 CRI Profile v2.0: GV.RM-02.01 CRI Profile v2.0: GV.RM-02.02 CRI Profile v2.0: GV.RM-02.03 CSF v1.1: ID.RM-2 CSF v1.1: ID.RM-3 SP 800-221A: GV.BE-1 SP 800-221A: GV.BE-3 SP 800-53 Rev 5.1.1: PM-09 | G9: Level 3: Managed | H9: =IF(G9="","",VLOOKUP(G9,'Maturity Definitions'!$B$4:$D$8,3,FALSE)) -> 3 | J9: Level 4: Quantitatively Managed | K9: =IF(J9="","",VLOOKUP(J9,'Maturity Definitions'!$B$4:$D$8,3,FALSE)) -> 4
A10: GOVERN (GV) | B10: Risk Management Strategy (GV.RM) | C10: GV.RM-03 | D10: Cybersecurity risk management activities and outcomes are included in enterprise risk management processes | E10: Ex1: Aggregate and manage cybersecurity risks alongside other enterprise risks (e.g., compliance, financial, operational, regulatory, reputational, safety) Ex2: Include cybersecurity risk managers in enterprise risk management planning Ex3: Establish criteria for escalating cybersecurity risks within enterprise risk management | F10: CCMv4.0: GRC-02 CCMv4.0: A&A-03 CRI Profile v2.0: GV.RM-03 CRI Profile v2.0: GV.RM-03.01 CRI Profile v2.0: GV.RM-03.02 CRI Profile v2.0: GV.RM-03.03 CRI Profile v2.0: GV.RM-03.04 CSF v1.1: ID.GV-4 SP 800-221A: GV.PO-2 SP 800-221A: GV.PO-3 SP 800-53 Rev 5.1.1: PM-03 SP 800-53 Rev 5.1.1: PM-09 SP 800-53 Rev 5.1.1: PM-30 SP 800-53 Rev 5.1.1: RA-07 SP 800-53 Rev 5.1.1: SR-02 | G10: Level 3: Managed | H10: =IF(G10="","",VLOOKUP(G10,'Maturity Definitions'!$B$4:$D$8,3,FALSE)) -> 3 | J10: Level 4: Quantitatively Managed | K10: =IF(J10="","",VLOOKUP(J10,'Maturity Definitions'!$B$4:$D$8,3,FALSE)) -> 4
A11: GOVERN (GV) | B11: Risk Management Strategy (GV.RM) | C11: GV.RM-04 | D11: Strategic direction that describes appropriate risk response options is established and communicated | E11: Ex1: Specify criteria for accepting and avoiding cybersecurity risk for various classifications of data Ex2: Determine whether to purchase cybersecurity insurance Ex3: Document conditions under which shared responsibility models are acceptable (e.g., outsourcing certain cybersecurity functions, having a third party perform financial transactions on behalf of the organization, using public cloud-based services) | F11: CCMv4.0: GRC-02 CCMv4.0: BCR-03 CCMv4.0: STA-01 CRI Profile v2.0: GV.RM-04 CRI Profile v2.0: GV.RM-04.01 CSF v1.1: ID.RM-2 SP 800-221A: GV.BE-1 SP 800-53 Rev 5.1.1: PM-09 SP 800-53 Rev 5.1.1: PM-28 SP 800-53 Rev 5.1.1: PM-30 SP 800-53 Rev 5.1.1: SR-02 | G11: Level 3: Managed | H11: =IF(G11="","",VLOOKUP(G11,'Maturity Definitions'!$B$4:$D$8,3,FALSE)) -> 3 | J11: Level 4: Quantitatively Managed | K11: =IF(J11="","",VLOOKUP(J11,'Maturity Definitions'!$B$4:$D$8,3,FALSE)) -> 4
A12: GOVERN (GV) | B12: Risk Management Strategy (GV.RM) | C12: GV.RM-05 | D12: Lines of communication across the organization are established for cybersecurity risks, including risks from suppliers and other third parties | E12: Ex1: Determine how to update senior executives, directors, and management on the organization's cybersecurity posture at agreed-upon intervals Ex2: Identify how all departments across the organization - such as management, operations, internal auditors, legal, acquisition, physical security, and HR - will communicate with each other about cybersecurity risks | F12: CCMv4.0: GRC-02 CCMv4.0: STA-01 CCMv4.0: STA-08 CRI Profile v2.0: GV.RM-05 CRI Profile v2.0: GV.RM-05.01 CRI Profile v2.0: GV.RM-05.02 CSF v1.1: ID.SC-1 SP 800-221A: GV.PO-1 SP 800-53 Rev 5.1.1: PM-09 SP 800-53 Rev 5.1.1: PM-30 | G12: Level 3: Managed | H12: =IF(G12="","",VLOOKUP(G12,'Maturity Definitions'!$B$4:$D$8,3,FALSE)) -> 3 | J12: Level 4: Quantitatively Managed | K12: =IF(J12="","",VLOOKUP(J12,'Maturity Definitions'!$B$4:$D$8,3,FALSE)) -> 4
A13: GOVERN (GV) | B13: Risk Management Strategy (GV.RM) | C13: GV.RM-06 | D13: A standardized method for calculating, documenting, categorizing, and prioritizing cybersecurity risks is established and communicated | E13: Ex1: Establish criteria for using a quantitative approach to cybersecurity risk analysis, and specify probability and exposure formulas Ex2: Create and use templates (e.g., a risk register) to document cybersecurity risk information (e.g., risk description, exposure, treatment, and ownership) Ex3: Establish criteria for risk prioritization at the appropriate levels within the enterprise Ex4: Use a consistent list of risk categories to support integrating, aggregating, and comparing cybersecurity risks | F13: CCMv4.0: GRC-02 CCMv4.0: TVM-08 CCMv4.0: IVS-08 CRI Profile v2.0: GV.RM-06 CRI Profile v2.0: GV.RM-06.01 CSF v1.1: ID.RM-1 SP 800-221A: GV.RR-2 SP 800-53 Rev 5.1.1: PM-09 SP 800-53 Rev 5.1.1: PM-18 SP 800-53 Rev 5.1.1: PM-28 SP 800-53 Rev 5.1.1: PM-30 SP 800-53 Rev 5.1.1: RA-03 | G13: Level 3: Managed | H13: =IF(G13="","",VLOOKUP(G13,'Maturity Definitions'!$B$4:$D$8,3,FALSE)) -> 3 | J13: Level 4: Quantitatively Managed | K13: =IF(J13="","",VLOOKUP(J13,'Maturity Definitions'!$B$4:$D$8,3,FALSE)) -> 4
A14: GOVERN (GV) | B14: Risk Management Strategy (GV.RM) | C14: GV.RM-07 | D14: Strategic opportunities (i.e., positive risks) are characterized and are included in organizational cybersecurity risk discussions | E14: Ex1: Define and communicate guidance and methods for identifying opportunities and including them in risk discussions (e.g., strengths, weaknesses, opportunities, and threats [SWOT] analysis) Ex2: Identify stretch goals and document them Ex3: Calculate, document, and prioritize positive risks alongside negative risks | F14: CCMv4.0: GRC-02 CRI Profile v2.0: GV.RM-07 CRI Profile v2.0: GV.RM-07.01 SP 800-53 Rev 5.1.1: PM-09 SP 800-53 Rev 5.1.1: PM-18 SP 800-53 Rev 5.1.1: PM-28 SP 800-53 Rev 5.1.1: PM-30 SP 800-53 Rev 5.1.1: RA-03 | G14: Level 3: Managed | H14: =IF(G14="","",VLOOKUP(G14,'Maturity Definitions'!$B$4:$D$8,3,FALSE)) -> 3 | J14: Level 4: Quantitatively Managed | K14: =IF(J14="","",VLOOKUP(J14,'Maturity Definitions'!$B$4:$D$8,3,FALSE)) -> 4
... A108: RECOVER (RC) | B108: Incident Recovery Communication (RC.CO) | C108: RC.CO-04 | D108: Public updates on incident recovery are shared using approved methods and messaging | E108: Ex1: Follow the organization's breach notification procedures for recovering from a data breach incident Ex2: Explain the steps being taken to recover from the incident and to prevent a recurrence | F108: CIS Controls v8.0: 17.2 CIS Controls v8.0: 17.6 CRI Profile v2.0: RC.CO-04 CRI Profile v2.0: RC.CO-04.01 CSF v1.1: RC.CO-1 CSF v1.1: RS.CO-2 SP 800-221A: GV.CO-1 SP 800-53 Rev 5.1.1: CP-02 SP 800-53 Rev 5.1.1: IR-04 | G108: Level 2: Documented | H108: =IF(G108="","",VLOOKUP(G108,'Maturity Definitions'!$B$4:$D$8,3,FALSE)) -> 2 | J108: Level 3: Managed | K108: =IF(J108="","",VLOOKUP(J108,'Maturity Definitions'!$B$4:$D$8,3,FALSE)) -> 3

Sheet Maturity Definitions
B3: Maturity Level | C3: Description of the level | D3: Score
B4: Level 1: Performed | C4: The organization may perform security practices in an ad hoc manner. | D4: 1
B5: Level 2: Documented | C5: The organization has established and documented practices related to security requirements. This documentation enables the organization to perform them in a repeatable manner and achieve expected outcomes. | D5: 2
B6: Level 3: Managed | C6: The organization reviews adherence to policies and provides adequate resources to implement and maintain security requirements. | D6: 3
B7: Level 4: Quantitatively Managed | C7: The organization reviews and measures practices for effectiveness. Corrective actions are taken when necessary, and higher-level management is informed of issues or status on a recurring basis. | D7: 4
B8: Level 5: Optimizing | C8: The organization has standardized and optimized process implementation throughout. It also communicates and shares improvement information across the organization. | D8: 5

Sheet Functions
B1: Function | C1: Function definition
B2: GOVERN (GV) | C2: The organization's cybersecurity risk management strategy, expectations, and policy are established, communicated, and monitored
B3: IDENTIFY (ID) | C3: The organization's current cybersecurity risks are understood
B4: PROTECT (PR) | C4: Safeguards to manage the organization's cybersecurity risks are used
B5: DETECT (DE) | C5: Possible cybersecurity attacks and compromises are found and analyzed
B6: RESPOND (RS) | C6: Actions regarding a detected cybersecurity incident are taken
B7: RECOVER (RC) | C7: Assets and operations affected by a cybersecurity incident are restored

Sheet Categories
B1: Category | C1: Category definition
B2: Organizational Context (GV.OC) | C2: The circumstances - mission, stakeholder expectations, dependencies, and legal, regulatory, and contractual requirements - surrounding the organization's cybersecurity risk management decisions are understood
B3: Risk Management Strategy (GV.RM) | C3: The organization's priorities, constraints, risk tolerance and appetite statements, and assumptions are established, communicated, and used to support operational risk decisions
B4: Roles, Responsibilities, and Authorities (GV.RR) | C4: Cybersecurity roles, responsibilities, and authorities to foster accountability, performance assessment, and continuous improvement are established and communicated
B5: Policy (GV.PO) | C5: Organizational cybersecurity policy is established, communicated, and enforced
B6: Oversight (GV.OV) | C6: Results of organization-wide cybersecurity risk management activities and performance are used to inform, improve, and adjust the risk management strategy
B7: Cybersecurity Supply Chain Risk Management (GV.SC) | C7: Cyber supply chain risk management processes are identified, established, managed, monitored, and improved by organizational stakeholders
B8: Asset Management (ID.AM) | C8: Assets (e.g., data, hardware, software, systems, facilities, services, people) that enable the organization to achieve business purposes are identified and managed consistent with their relative importance to organizational objectives and the organization's risk strategy
B9: Risk Assessment (ID.RA) | C9: The cybersecurity risk to the organization, assets, and individuals is understood by the organization
B10: Improvement (ID.IM) | C10: Improvements to organizational cybersecurity risk management processes, procedures and activities are identified across all CSF Functions
B11: Identity Management, Authentication, and Access Control (PR.AA) | C11: Access to physical and logical assets is limited to authorized users, services, and hardware and managed commensurate with the assessed risk of unauthorized access
B12: Awareness and Training (PR.AT) | C12: The organization's personnel are provided with cybersecurity awareness and training so that they can perform their cybersecurity-related tasks
... B23: Incident Recovery Communication (RC.CO) | C23: Restoration activities are coordinated with internal and external parties
